ibridgesgui/__init__.py
ibridgesgui/__main__.py
ibridgesgui/_version.py
ibridgesgui/browser.py
ibridgesgui/config.py
ibridgesgui/gui_utils.py
ibridgesgui/info.py
ibridgesgui/irods_tree_model.py
ibridgesgui/login.py
ibridgesgui/logviewer.py
ibridgesgui/popup_widgets.py
ibridgesgui/search.py
ibridgesgui/sync.py
ibridgesgui/threads.py
ibridgesgui/welcome.py
ibridgesgui/icons/arrow-left.png
ibridgesgui/icons/arrow-right.png
ibridgesgui/icons/arrow-up.png
ibridgesgui/icons/christmas-logo.png
ibridgesgui/icons/home.png
ibridgesgui/icons/iBridges.ico
ibridgesgui/icons/loading_circle.gif
ibridgesgui/icons/logo.png
ibridgesgui/icons/nosync.png
ibridgesgui/icons/refresh.png
ibridgesgui/icons/syncing.png
ibridgesgui/ui_files/MainMenu.py
ibridgesgui/ui_files/MainMenu.ui
ibridgesgui/ui_files/__init__.py
ibridgesgui/ui_files/configCheck.py
ibridgesgui/ui_files/configCheck.ui
ibridgesgui/ui_files/createCollection.py
ibridgesgui/ui_files/createCollection.ui
ibridgesgui/ui_files/downloadData.py
ibridgesgui/ui_files/downloadData.ui
ibridgesgui/ui_files/irodsLogin.py
ibridgesgui/ui_files/irodsLogin.ui
ibridgesgui/ui_files/renameItem.py
ibridgesgui/ui_files/renameItem.ui
ibridgesgui/ui_files/tabBrowser.py
ibridgesgui/ui_files/tabBrowser.ui
ibridgesgui/ui_files/tabInfo.py
ibridgesgui/ui_files/tabInfo.ui
ibridgesgui/ui_files/tabLogging.py
ibridgesgui/ui_files/tabLogging.ui
ibridgesgui/ui_files/tabSearch.py
ibridgesgui/ui_files/tabSearch.ui
ibridgesgui/ui_files/tabSync.py
ibridgesgui/ui_files/tabSync.ui
ibridgesgui/ui_files/transferData.py
ibridgesgui/ui_files/transferData.ui
ibridgesgui/ui_files/uploadData.py
ibridgesgui/ui_files/uploadData.ui
ibridgesgui/ui_files/welcome.py
ibridgesgui/ui_files/welcome.ui
ibridgesgui-2.0.0.dist-info/licenses/LICENSE
ibridgesgui-2.0.0.dist-info/METADATA
ibridgesgui-2.0.0.dist-info/WHEEL
ibridgesgui-2.0.0.dist-info/top_level.txt
ibridgesgui-2.0.0.dist-info/RECORD
