Metadata-Version: 2.4
Name: ibridgesgui
Version: 2.0.0
Summary: Graphical user interface for accessing data and metadata on iRODS servers.
Author-email: Christine Staiger <c.staiger@uu.nl>
License:                   GNU LESSER GENERAL PUBLIC LICENSE
Project-URL: GitHub, https://github.com/chStaiger/iBridges-Gui
Project-URL: documentation, https://github.com/chStaiger/iBridges-Gui
Keywords: irods,data management,storage
Classifier: Programming Language :: Python :: 3
Classifier: Programming Language :: Python :: 3.9
Classifier: Programming Language :: Python :: 3.10
Classifier: Programming Language :: Python :: 3.11
Classifier: Programming Language :: Python :: 3.12
Classifier: Development Status :: 3 - Alpha
Requires-Python: >=3.9
License-File: LICENSE
Requires-Dist: PySide6>=6.8.1
Requires-Dist: ibridges<2.1,>=2.0.0
Requires-Dist: setproctitle==1.3.7
Requires-Dist: importlib-resources; python_version <= "3.10"
Provides-Extra: test
Requires-Dist: pylint; extra == "test"
Requires-Dist: pytest; extra == "test"
Requires-Dist: pytest-cov; extra == "test"
Requires-Dist: ruff; extra == "test"
Requires-Dist: mypy; extra == "test"
Provides-Extra: deploy
Requires-Dist: Nuitka; extra == "deploy"
Requires-Dist: imageio; extra == "deploy"
Provides-Extra: all
Requires-Dist: ibridgesgui[deploy,test]; extra == "all"
Dynamic: license-file
